LICENSE
README.md
setup.py
dss_toolkit/__init__.py
dss_toolkit/date_utils.py
dss_toolkit/storage.py
dss_toolkit.egg-info/PKG-INFO
dss_toolkit.egg-info/SOURCES.txt
dss_toolkit.egg-info/dependency_links.txt
dss_toolkit.egg-info/requires.txt
dss_toolkit.egg-info/top_level.txt
dss_toolkit/data_analysis/__init__.py
dss_toolkit/data_analysis/visualization.py
dss_toolkit/data_build_old/__init__.py
dss_toolkit/data_build_old/cleaning.py
dss_toolkit/data_build_old/feature_selection.py
dss_toolkit/modeling/__init__.py
dss_toolkit/modeling/base.py
dss_toolkit/modeling/hyperparameter_tuner.py
dss_toolkit/modeling/model_builder.py
dss_toolkit/modeling/model_metrics_old.py
dss_toolkit/modeling/optimization.py
dss_toolkit/modeling/preprocessing.py
dss_toolkit/modeling/smote.py
dss_toolkit/modeling/algorithms/__init__.py
dss_toolkit/modeling/algorithms/cluster.py
dss_toolkit/modeling/algorithms/linear_model.py
dss_toolkit/modeling/algorithms/neural_net.py
dss_toolkit/modeling/algorithms/xgboost.py
dss_toolkit/preprocessing/__init__.py
dss_toolkit/preprocessing/cleaning.py
dss_toolkit/preprocessing/cleaning_old.py
dss_toolkit/preprocessing/custom_estimator.py
dss_toolkit/preprocessing/data_dictionary.py
dss_toolkit/preprocessing/data_preprocessor.py
dss_toolkit/preprocessing/data_validation.py
dss_toolkit/preprocessing/eda.py
dss_toolkit/preprocessing/feature_selection.py
dss_toolkit/preprocessing/feature_transformer.py
dss_toolkit/preprocessing/outlier.py