Metadata-Version: 1.0
Name: dss-toolkit
Version: 0.1.0
Summary: Library for commonly used code for Data Science Experiments
Home-page: UNKNOWN
Author: Joseph Benjamin Del Mundo
Author-email: jbdelmundo@gmail.com
License: UNKNOWN
Platform: UNKNOWN
